ppyorthanc/__init__.py
ppyorthanc/async_client.py
ppyorthanc/client.py
ppyorthanc/deprecated/__init__.py
ppyorthanc/deprecated/client.py
ppyorthanc/filtering.py
ppyorthanc/instance.py
ppyorthanc/patient.py
ppyorthanc/remote.py
ppyorthanc/series.py
ppyorthanc/study.py
ppyorthanc/util.py
ppyorthanc-2.0.0.dist-info/LICENSE.txt
ppyorthanc-2.0.0.dist-info/WHEEL
ppyorthanc-2.0.0.dist-info/METADATA
ppyorthanc-2.0.0.dist-info/RECORD
