Metadata-Version: 2.1
Name: ppyorthanc
Version: 2.0.0
Summary: Orthanc REST API python wrapper with additional utilities
License: MIT
Author: Gabriel Couture
Author-email: gacou54@gmail.com
Requires-Python: >=3.8,<4.0
Classifier: License :: OSI Approved :: MIT License
Classifier: Programming Language :: Python :: 3
Classifier: Programming Language :: Python :: 3.8
Classifier: Programming Language :: Python :: 3.9
Classifier: Programming Language :: Python :: 3.10
Requires-Dist: httpx (>=0.23.0,<0.24.0)
Requires-Dist: pydicom (>=2.3.0,<3.0.0)
